<?xml version="1.0" encoding="UTF-7"?>
<INTERFAZ>
<MENSAJES>
<MSG id="1" tam="35">  ERRO AO OBTER TIPOIMPRESORA</MSG>
<MSG id="2" tam="33"> ERRO AO OBTER FIN DE LINEA</MSG>
</MENSAJES>
<REPORTES/>
<DLG_01>
<CONTROLES>
<CTR id="63152" tam="15">FOLIO SEGURANÇA</CTR>
<CTR id="63153" tam="54">SELECCIONADOS COM A BARRA DE ESPAÇO DOS ENUNCIADOS</CTR>
<CTR id="63155" tam="32">DOCUMENTAÇÃO DE SEGURO DE VIDA</CTR>
<CTR id="63156" tam="45">CONTRATO INICIAL E FINAL RECIBO DE PAGAMENTO.</CTR>
<CTR id="63157" tam="45">ORIGINAL CERTIDÃO DE NASCIMENTO DA SEGURADORA.</CTR>
<CTR id="63158" tam="30">CERTIDÃO DE DEFUNCIÓN ORIGINAL.</CTR>
<CTR id="63159" tam="60">COMPLETAMENTE ENCHE AS DECLARAÇÕES DA SEGURADORA.</CTR>
<CTR id="63160" tam="59">CÓPIA DE CLÍNICAS OU ÓBITO.</CTR>
<CTR id="63161" tam="61">CERTIDÃO DE ACÇÃO PENAL (EM CASOS DE MORTE VIOLENTA).</CTR>
<CTR id="63162" tam="87">ORIGINAL CERTIDÃO DE NASCIMENTO DOS BENEFICIÁRIOS E DE CÓPIAS DE UMA IDENTIFICAÇÃO COM FOTO.</CTR>
<CTR id="63164" tam="108">CERTIDÃO DE NASCIMENTO ORIGINAIS E CÓPIAS DA IDENTIFICAÇÃO DE BENEFICIÁRIOS GUARDIAN, EM CASO DE MENORES.</CTR>
<CTR id="63165" tam="76">CERTIDÃO NOTÁRIO DA PESSOA QUE TEM AUTORIDADE PARENTAL OU TUTELA DOS MENORES.</CTR>
</CONTROLES>
<MENSAJES>
<MSG id="1" tam="39">[ ESC ] Cancel      [ F10 ] Imprimir</MSG>
<MSG id="2" tam="19">FOLIO INCORRETO</MSG>
<MSG id="3" tam="35">FAVOR DE TECLEAR NÚMERO DE FOLIO</MSG>
<MSG id="4" tam="44">FAVOR DE TECLEAR NÚMERO DE FOLIO CORRETO</MSG>
</MENSAJES>
<REPORTES>
<RPE id="1" tam="47">VOCÊ TERÁ PEGO OS SEGUINTES DOCUMENTOS:</RPE>
<RPE id="2" tam="39">ORIGINAL CTO ÚLTIMO PAGAMENTO E DE RECEBIMENTO</RPE>
<RPE id="3" tam="39">ORIGINAL CTO ÚLTIMO PAGAMENTO E DE RECEBIMENTO</RPE>
<RPE id="4" tam="39">CERTIDÃO DO ORIGINAL NACT SEGURADORA</RPE>
<RPE id="5" tam="39">CERTIDÃO DO ORIGINAL NACT SEGURADORA</RPE>
<RPE id="6" tam="29">CERTIDÃO ORIGINAL MORTE</RPE>
<RPE id="7" tam="29">CERTIDÃO ORIGINAL MORTE</RPE>
<RPE id="8" tam="34">DECLARAÇÃO DA SEGURADORA</RPE>
<RPE id="9" tam="34">DECLARAÇÃO DA SEGURADORA</RPE>
<RPE id="10" tam="38">EXPTE CLINICO O CERTDO DE DEFUNCION</RPE>
<RPE id="11" tam="38">EXPTE CLINICO O CERTDO DE DEFUNCION</RPE>
<RPE id="12" tam="30">CERTIDÃO DEL MINISTERIO PUBLICO</RPE>
<RPE id="13" tam="30">CERTIDÃO DEL MINISTERIO PUBLICO</RPE>
<RPE id="14" tam="36">CERTIDÃO ORIGINAL DE BENEF E IDENTIFI</RPE>
<RPE id="15" tam="36">CERTIDÃO ORIGINAL DE BENEF E IDENTIFI</RPE>
<RPE id="16" tam="37">REGISTRO DE IDENTIFICAÇÃO DO ORIGINAL E TUTOR</RPE>
<RPE id="17" tam="37">REGISTRO DE IDENTIFICAÇÃO DO ORIGINAL E TUTOR</RPE>
<RPE id="18" tam="40">CERTIDÃO NOTÁRIO DA PÁTRIA PROTESTO</RPE>
<RPE id="19" tam="40">CERTIDÃO NOTÁRIO DA PÁTRIA PROTESTO</RPE>
<RPE id="20" tam="24">      F I R M A      </RPE>
<RPE id="21" tam="29">Houve um erro ao gravar</RPE>
</REPORTES>
</DLG_01>
</INTERFAZ>
